fides/__init__.py
fides/_version.py
fides/py.typed
fides/api/__init__.py
fides/api/main.py
fides/api/ctl/__init__.py
fides/api/ctl/alembic.ini
fides/api/ctl/sql_models.py
fides/api/ctl/ui.py
fides/api/ctl/view.py
fides/api/ctl/database/__init__.py
fides/api/ctl/database/crud.py
fides/api/ctl/database/database.py
fides/api/ctl/database/seed.py
fides/api/ctl/database/session.py
fides/api/ctl/migrations/__init__.py
fides/api/ctl/migrations/env.py
fides/api/ctl/migrations/versions/0210948a8147_initial.py
fides/api/ctl/migrations/versions/021d288d0ce3_add_consent_request.py
fides/api/ctl/migrations/versions/07014ff34eb2_add_mariadb.py
fides/api/ctl/migrations/versions/150f234ef1de_add_fidesctl_meta_to_organization_object.py
fides/api/ctl/migrations/versions/155fd8e51d9d_add_fideslib_models.py
fides/api/ctl/migrations/versions/1739aa4a4ab7_add_security_policy_link_and_erasure_.py
fides/api/ctl/migrations/versions/179f2bb623ae_update_table_for_twilio.py
fides/api/ctl/migrations/versions/1dfc5a2d30e7_add_saas_config_to_connection_config.py
fides/api/ctl/migrations/versions/1f61c765cd1c_merge_alembic_heads.py
fides/api/ctl/migrations/versions/1ff88b7bd579_add_authorization_request.py
fides/api/ctl/migrations/versions/216cdc7944f1_add_datasetconfig_ctl_datasets_fk.py
fides/api/ctl/migrations/versions/25adddf820a3_another_fidesops_remote_merge.py
fides/api/ctl/migrations/versions/26934c96ec80_initial_migration.py
fides/api/ctl/migrations/versions/27fe9da9d0f9_privacy_request_stopped.py
fides/api/ctl/migrations/versions/28108b17a99c_add_notifications_for_failed_dsr_.py
fides/api/ctl/migrations/versions/29a7d707163a_adds_first_name_and_last_name_to_user_.py
fides/api/ctl/migrations/versions/2fb48b0e268b_update_ctl_datasets_fidesctl_meta.py
fides/api/ctl/migrations/versions/312aff72b275_migrate_to_usage_of_evaluation_.py
fides/api/ctl/migrations/versions/327cd266f7b3_update_dataset_depth.py
meld_sandbox-2.7.8.dist-info/LICENSE
meld_sandbox-2.7.8.dist-info/METADATA
meld_sandbox-2.7.8.dist-info/WHEEL
meld_sandbox-2.7.8.dist-info/entry_points.txt
meld_sandbox-2.7.8.dist-info/top_level.txt
meld_sandbox-2.7.8.dist-info/RECORD
